mdsisclienttools/__init__.py
mdsisclienttools/auth/TokenManager.py
mdsisclienttools/auth/__init__.py
mdsisclienttools/datastore/ReadWriteHelper.py
mdsisclienttools/datastore/__init__.py
mdsisclienttools/py.typed
mdsisclienttools-1.5.7.dist-info/METADATA
mdsisclienttools-1.5.7.dist-info/WHEEL
mdsisclienttools-1.5.7.dist-info/RECORD
