Metadata-Version: 2.1
Name: mdsisclienttools
Version: 1.5.7
Summary: Python package containing client tools to assist in accessing and using the RRAP M&DS IS APIs and services.
License: None
Author: RRAP
Author-email: rrapisdev@gmail.com
Requires-Python: >=3.8,<4.0
Classifier: License :: Other/Proprietary License
Classifier: Programming Language :: Python :: 3
Classifier: Programming Language :: Python :: 3.8
Classifier: Programming Language :: Python :: 3.9
Classifier: Programming Language :: Python :: 3.10
Classifier: Programming Language :: Python :: 3.11
Requires-Dist: botocore (<=1.30.1)
Requires-Dist: cloudpathlib[s3] (<=0.15.1)
Requires-Dist: pydantic (<=1.10.13)
Requires-Dist: python-jose (>=3.3.0,<4.0.0)
Requires-Dist: requests (<=2.28.1)
Requires-Dist: types-requests (>=2.28.3,<3.0.0)
